{
  "date": "2026-05-19",
  "generated_at": "2026-05-19T16:00:00-04:00",
  "is_holiday": false,
  "market": "us",
  "payload": {
    "indices": {
      "^DJI": {
        "close": 49363.87890625,
        "date": "2026-05-19",
        "label": "다우",
        "pct": -0.6485557342904249,
        "vol_ratio": 0.9749081910886251
      },
      "^GSPC": {
        "close": 7353.60986328125,
        "date": "2026-05-19",
        "label": "S&P500",
        "pct": -0.6678320788135907,
        "vol_ratio": 0.9828645293119475
      },
      "^IXIC": {
        "close": 25870.7109375,
        "date": "2026-05-19",
        "label": "나스닥",
        "pct": -0.8432862066224129,
        "vol_ratio": 1.0069010372415061
      },
      "^RUT": {
        "close": 2747.070068359375,
        "date": "2026-05-19",
        "label": "러셀2000",
        "pct": -1.010054711920055,
        "vol_ratio": 0.9828645293119475
      }
    },
    "macro": {
      "CL=F": {
        "close": 107.7699966430664,
        "date": "2026-05-19",
        "label": "WTI",
        "pct": -0.8190750865521288,
        "vol_ratio": 1.2398442088120742
      },
      "DX-Y.NYB": {
        "close": 99.30000305175781,
        "date": "2026-05-19",
        "label": "DXY",
        "pct": 0.33343622005094586,
        "vol_ratio": null
      },
      "GC=F": {
        "close": 4506.2998046875,
        "date": "2026-05-19",
        "label": "금",
        "pct": -1.014831308347062,
        "vol_ratio": 4.505664263645726
      },
      "KRW=X": {
        "close": 1492.3199462890625,
        "date": "2026-05-19",
        "label": "원달러",
        "pct": -0.32261817761986417,
        "vol_ratio": null
      },
      "^TNX": {
        "close": 4.666999816894531,
        "date": "2026-05-19",
        "label": "10Y금리",
        "pct": 0.951755798321096,
        "vol_ratio": null
      },
      "^TYX": {
        "close": 5.181000232696533,
        "date": "2026-05-19",
        "label": "30Y금리",
        "pct": 0.660586707054383,
        "vol_ratio": null
      }
    },
    "risk_onoff": {
      "HYG": {
        "close": 79.3499984741211,
        "date": "2026-05-19",
        "label": "고수익채권",
        "pct": -0.23887658941321288,
        "vol_ratio": 1.1233143621346813
      },
      "IEF": {
        "close": 93.11000061035156,
        "date": "2026-05-19",
        "label": "7-10Y국채",
        "pct": -0.38515096357121287,
        "vol_ratio": 1.4289565997252716
      }
    },
    "sectors": {
      "XLB": {
        "close": 49.040000915527344,
        "date": "2026-05-19",
        "label": "소재",
        "pct": -2.3496620400107195,
        "vol_ratio": 1.131767955801105
      },
      "XLC": {
        "close": 115.8499984741211,
        "date": "2026-05-19",
        "label": "통신",
        "pct": -0.965981236437982,
        "vol_ratio": 1.1538667798806783
      },
      "XLE": {
        "close": 61.290000915527344,
        "date": "2026-05-19",
        "label": "에너지",
        "pct": 1.1720024150093282,
        "vol_ratio": 0.9839598509211163
      },
      "XLF": {
        "close": 51.099998474121094,
        "date": "2026-05-19",
        "label": "금융",
        "pct": -1.236960153814723,
        "vol_ratio": 1.0130932389635858
      },
      "XLI": {
        "close": 168.74000549316406,
        "date": "2026-05-19",
        "label": "산업",
        "pct": -1.1771563729639458,
        "vol_ratio": 1.002442178615707
      },
      "XLK": {
        "close": 173.24000549316406,
        "date": "2026-05-19",
        "label": "기술",
        "pct": -0.642346359983327,
        "vol_ratio": 1.1112083087007991
      },
      "XLP": {
        "close": 86.08999633789062,
        "date": "2026-05-19",
        "label": "필수소비",
        "pct": 0.22118138374477145,
        "vol_ratio": 1.0719380584014777
      },
      "XLRE": {
        "close": 43.939998626708984,
        "date": "2026-05-19",
        "label": "리츠",
        "pct": 0.43428257533482145,
        "vol_ratio": 0.8321029521458617
      },
      "XLU": {
        "close": 44.34000015258789,
        "date": "2026-05-19",
        "label": "유틸",
        "pct": 0.9103357723724753,
        "vol_ratio": 0.8755168026098581
      },
      "XLV": {
        "close": 147.32000732421875,
        "date": "2026-05-19",
        "label": "헬스케어",
        "pct": 1.098000336338389,
        "vol_ratio": 1.1800106302115183
      },
      "XLY": {
        "close": 115.02999877929688,
        "date": "2026-05-19",
        "label": "임의소비",
        "pct": -1.1090104185967804,
        "vol_ratio": 1.1395179544947343
      }
    },
    "volatility": {
      "^SKEW": {
        "close": 135.5,
        "date": "2026-05-19",
        "label": "SKEW",
        "pct": -2.0953714048957344,
        "vol_ratio": null
      },
      "^VIX": {
        "close": 18.059999465942383,
        "date": "2026-05-19",
        "label": "VIX",
        "pct": 1.3468000854560704,
        "vol_ratio": null
      },
      "^VVIX": {
        "close": 94.61000061035156,
        "date": "2026-05-19",
        "label": "VVIX",
        "pct": 3.761790188304133,
        "vol_ratio": null
      }
    },
    "watch": {
      "GLD": {
        "close": 411.5,
        "date": "2026-05-19",
        "label": "금",
        "pct": -1.6561892782745442,
        "vol_ratio": 0.9077326615591281
      },
      "ITA": {
        "close": 218.32000732421875,
        "date": "2026-05-19",
        "label": "방산",
        "pct": -0.8672698725759792,
        "vol_ratio": 1.4954303353104952
      },
      "NLR": {
        "close": 125.05999755859375,
        "date": "2026-05-19",
        "label": "원자력",
        "pct": -1.9368001602334393,
        "vol_ratio": 0.7754027858013993
      },
      "QQQ": {
        "close": 701.530029296875,
        "date": "2026-05-19",
        "label": "나스닥100",
        "pct": -0.6162485912403293,
        "vol_ratio": 1.0602123164170292
      },
      "SLV": {
        "close": 66.9000015258789,
        "date": "2026-05-19",
        "label": "은",
        "pct": -4.3465839425358475,
        "vol_ratio": 0.7303024870566757
      },
      "SMH": {
        "close": 543.9600219726562,
        "date": "2026-05-19",
        "label": "반도체",
        "pct": -0.4028034422238451,
        "vol_ratio": 0.9743949009138482
      },
      "XLE": {
        "close": 61.290000915527344,
        "date": "2026-05-19",
        "label": "에너지",
        "pct": 1.1720024150093282,
        "vol_ratio": 0.9839598509211163
      },
      "XOVR": {
        "close": 19.079999923706055,
        "date": "2026-05-19",
        "label": "SpaceX",
        "pct": -0.46948436217893835,
        "vol_ratio": 1.0680686574423695
      }
    }
  },
  "schema_version": 1,
  "sources": [
    {
      "label": "Yahoo Finance",
      "url": "https://finance.yahoo.com/markets/"
    },
    {
      "label": "S&P 섹터",
      "url": "https://finance.yahoo.com/sectors/"
    }
  ]
}
